lmnr_cli/__init__.py
lmnr_cli/__main__.py
lmnr_cli/cli.py
lmnr_cli/cookiecutter.json
lmnr_cli/parser/__init__.py
lmnr_cli/parser/nodes/__init__.py
lmnr_cli/parser/nodes/types.py
lmnr_cli/parser/parser.py
lmnr_cli/parser/utils.py
lmnr_cli/{{cookiecutter.lmnr_pipelines_dir_name}}/__init__.py
lmnr_cli/{{cookiecutter.lmnr_pipelines_dir_name}}/engine/__init__.py
lmnr_cli/{{cookiecutter.lmnr_pipelines_dir_name}}/engine/action.py
lmnr_cli/{{cookiecutter.lmnr_pipelines_dir_name}}/engine/engine.py
lmnr_cli/{{cookiecutter.lmnr_pipelines_dir_name}}/engine/state.py
lmnr_cli/{{cookiecutter.lmnr_pipelines_dir_name}}/engine/task.py
lmnr_cli/{{cookiecutter.lmnr_pipelines_dir_name}}/pipelines/{{cookiecutter.pipeline_dir_name}}/__init__.py
lmnr_cli/{{cookiecutter.lmnr_pipelines_dir_name}}/pipelines/{{cookiecutter.pipeline_dir_name}}/nodes/functions.py
lmnr_cli/{{cookiecutter.lmnr_pipelines_dir_name}}/pipelines/{{cookiecutter.pipeline_dir_name}}/{{cookiecutter.pipeline_dir_name}}.py
lmnr_cli/{{cookiecutter.lmnr_pipelines_dir_name}}/types.py
lmnr_cli-0.0.4.dist-info/METADATA
lmnr_cli-0.0.4.dist-info/WHEEL
lmnr_cli-0.0.4.dist-info/entry_points.txt
lmnr_cli-0.0.4.dist-info/RECORD
