Metadata-Version: 2.1
Name: lmnr_cli
Version: 0.0.4
Summary: 
Author: Laminar
Author-email: founders@lmnr.ai
Requires-Python: >=3.9,<4.0
Classifier: Programming Language :: Python :: 3
Classifier: Programming Language :: Python :: 3.9
Classifier: Programming Language :: Python :: 3.10
Classifier: Programming Language :: Python :: 3.11
Classifier: Programming Language :: Python :: 3.12
Requires-Dist: black (>=24.4.2,<25.0.0)
Requires-Dist: click (>=8.1.7,<9.0.0)
Requires-Dist: cookiecutter (>=2.6.0,<3.0.0)
Requires-Dist: python-dotenv (>=1.0.1,<2.0.0)
Requires-Dist: urllib3 (==1.26.6)
